pygdk/__init__.py
pygdk/assets/icons/pygdk.ico
pygdk/core/Gk.py
pygdk/core/GkWidgets.py
pygdk/core/__init__.py
pygdk-1.0.3.dist-info/LICENSE
pygdk-1.0.3.dist-info/METADATA
pygdk-1.0.3.dist-info/WHEEL
pygdk-1.0.3.dist-info/top_level.txt
pygdk-1.0.3.dist-info/RECORD
