Metadata-Version: 2.1
Name: pygdk
Version: 1.0.3
Summary: Python General Development Kit
License: MIT
Project-URL: Issue Tracker, https://github.com/pygdk/pygdk/issues
Project-URL: Source, https://github.com/pygdk/pygdk
Keywords: GUI,Cross-Platform,Lightweight,Fast
Platform: any
Classifier: Development Status :: 3 - Alpha
Classifier: Intended Audience :: Developers
Classifier: License :: OSI Approved :: MIT License
Classifier: Operating System :: OS Independent
Classifier: Programming Language :: Python
Classifier: Programming Language :: Python :: 3
Classifier: Topic :: Software Development :: User Interfaces
Classifier: Topic :: Multimedia :: Graphics
License-File: LICENSE
Requires-Dist: typing
Provides-Extra: dev
Requires-Dist: mypy; extra == "dev"
